lims_connector/__init__.py
lims_connector/connectToLIMS.py
lims_connector/setConfig.py
tests/TestLIMSClient.py
tests/__init__.py
lims_connector-1.0.1.dist-info/METADATA
lims_connector-1.0.1.dist-info/WHEEL
lims_connector-1.0.1.dist-info/top_level.txt
lims_connector-1.0.1.dist-info/RECORD
